<?xml version="1.0" encoding="utf-8"?>
<install version="1.5" type="plugin"  group="sso">
	<name>SSO - eDirectory LDAP</name>
	<author>Sam Moffatt</author>
	<creationDate>April 2007</creationDate>
	<copyright>(C) 2007 Toowoomba City Council/Sam Moffatt. All rights reserved.</copyright>
	<license>http://www.gnu.org/copyleft/gpl.html GNU/GPL</license>
	<authorEmail>S.Moffatt@toowoomba.qld.gov.au</authorEmail>
	<authorUrl>imb.toowoomba.qld.gov.au</authorUrl>
	<version id="2">1.5.1</version>
	<update>http://www.jsitepoint.com/update/plugins/plgssoedirldap</update>
	<description>Handles user detection using eDirectory's networkAddress attribute</description>
	<files>
		<filename plugin="edirldap">edirldap.php</filename>
	</files>
		<params>
			<param name="ip_blacklist" default="127.0.0.1" type="textarea" cols="30" rows="10" label="IP Blacklist" description="IP addresses to ignore for Single Sign OnIP addresses to ignore for Single Sign On (newline seperated)"/>
		</params>
</install>
